{
    "derniere_mise_a_jour": "02/04/2026 à 23:00",
    "horodatage_fin_recherche": "2026-04-02T23:00:00",
    "total_france_twh": 105.274,
    "nombre_centrales_actives": 18,
    "nombre_reacteurs_total": 57,
    "nombre_reacteurs_en_production": 44,
    "production_par_centrale_twh": {
        "GRAVELINES": 9.571,
        "CATTENOM": 8.421,
        "PALUEL": 7.991,
        "BUGEY": 6.923,
        "TRICASTIN": 6.843,
        "CHINON": 6.769,
        "DAMPIERRE": 6.235,
        "CIVAUX": 5.886,
        "CRUAS": 5.788,
        "BLAYAIS": 5.731,
        "NOGENT": 5.552,
        "PENLY": 4.873,
        "BELLEVILLE": 4.686,
        "GOLFECH": 4.372,
        "ST ALBAN": 4.329,
        "FLAMANVILLE": 3.865,
        "CHOOZ": 3.818,
        "ST LAURENT": 3.623
    },
    "cache_brut_mwh": {
        "BELLEVILLE 1": 2458702.0,
        "BELLEVILLE 2": 2227316.0,
        "BLAYAIS 1": 1716713.0,
        "BLAYAIS 2": 1896510.0,
        "BLAYAIS 3": 277894.0,
        "BLAYAIS 4": 1840229.0,
        "BUGEY 2": 1960256.0,
        "BUGEY 3": 1965616.0,
        "BUGEY 4": 1869106.0,
        "BUGEY 5": 1128451.0,
        "CATTENOM 1": 2146165.0,
        "CATTENOM 2": 2714426.0,
        "CATTENOM 3": 2782655.0,
        "CATTENOM 4": 777874.0,
        "CHINON 1": 1154558.0,
        "CHINON 2": 1892081.0,
        "CHINON 3": 1839020.0,
        "CHINON 4": 1882898.0,
        "CHOOZ 1": 2387373.0,
        "CHOOZ 2": 1430626.0,
        "CIVAUX 1": 2909917.0,
        "CIVAUX 2": 2975912.0,
        "CRUAS 1": 1935778.0,
        "CRUAS 2": 1266456.0,
        "CRUAS 3": 647656.0,
        "CRUAS 4": 1937752.0,
        "DAMPIERRE 1": 1516565.0,
        "DAMPIERRE 2": 950532.0,
        "DAMPIERRE 3": 1941146.0,
        "DAMPIERRE 4": 1826481.0,
        "FLAMANVILLE 1": 1871485.0,
        "FLAMANVILLE 2": 245.0,
        "GOLFECH 1": 2662154.0,
        "GOLFECH 2": 1710122.0,
        "GRAVELINES 1": 756047.0,
        "GRAVELINES 2": 1280386.0,
        "GRAVELINES 3": 1944959.0,
        "GRAVELINES 4": 1858387.0,
        "GRAVELINES 5": 1951265.0,
        "GRAVELINES 6": 1779505.0,
        "NOGENT 1": 2763529.0,
        "NOGENT 2": 2788101.0,
        "PALUEL 1": 47713.0,
        "PALUEL 2": 2636998.0,
        "PALUEL 3": 2713314.0,
        "PALUEL 4": 2592816.0,
        "PENLY 1": 2123048.0,
        "PENLY 2": 2749939.0,
        "ST ALBAN 1": 1594286.0,
        "ST ALBAN 2": 2734502.0,
        "ST LAURENT 1": 1926479.0,
        "ST LAURENT 2": 1696707.0,
        "TRICASTIN 1": 1208366.0,
        "TRICASTIN 2": 1909411.0,
        "TRICASTIN 3": 1727002.0,
        "TRICASTIN 4": 1998098.0,
        "FLAMANVILLE 3": 1992820.0
    },
    "cache_statut": {
        "BELLEVILLE 1": true,
        "BELLEVILLE 2": true,
        "BLAYAIS 1": true,
        "BLAYAIS 2": false,
        "BLAYAIS 3": false,
        "BLAYAIS 4": true,
        "BUGEY 2": true,
        "BUGEY 3": true,
        "BUGEY 4": true,
        "BUGEY 5": false,
        "CATTENOM 1": true,
        "CATTENOM 2": true,
        "CATTENOM 3": true,
        "CATTENOM 4": false,
        "CHINON 1": true,
        "CHINON 2": true,
        "CHINON 3": true,
        "CHINON 4": true,
        "CHOOZ 1": true,
        "CHOOZ 2": false,
        "CIVAUX 1": true,
        "CIVAUX 2": true,
        "CRUAS 1": true,
        "CRUAS 2": true,
        "CRUAS 3": false,
        "CRUAS 4": true,
        "DAMPIERRE 1": true,
        "DAMPIERRE 2": true,
        "DAMPIERRE 3": true,
        "DAMPIERRE 4": true,
        "FLAMANVILLE 1": true,
        "FLAMANVILLE 2": false,
        "GOLFECH 1": true,
        "GOLFECH 2": true,
        "GRAVELINES 1": true,
        "GRAVELINES 2": true,
        "GRAVELINES 3": true,
        "GRAVELINES 4": false,
        "GRAVELINES 5": true,
        "GRAVELINES 6": true,
        "NOGENT 1": true,
        "NOGENT 2": true,
        "PALUEL 1": false,
        "PALUEL 2": true,
        "PALUEL 3": true,
        "PALUEL 4": true,
        "PENLY 1": false,
        "PENLY 2": true,
        "ST ALBAN 1": false,
        "ST ALBAN 2": true,
        "ST LAURENT 1": false,
        "ST LAURENT 2": true,
        "TRICASTIN 1": false,
        "TRICASTIN 2": true,
        "TRICASTIN 3": true,
        "TRICASTIN 4": true,
        "FLAMANVILLE 3": true
    }
}